easypath/__init__.py
easypath/main.py
easypath/test.py
easypath-0.1.0.dist-info/licenses/LICENSE.txt
easypath-0.1.0.dist-info/METADATA
easypath-0.1.0.dist-info/WHEEL
easypath-0.1.0.dist-info/top_level.txt
easypath-0.1.0.dist-info/RECORD
