Metadata-Version: 2.4
Name: easypath
Version: 0.1.0
Summary: Cross-platform file and folder utility functions in Python made simple.
Home-page: https://github.com/aaravmaloo/easypath
Author: Aarav Maloo
Author-email: aaravmaloo06@gmail.com
Classifier: Development Status :: 3 - Alpha
Classifier: Programming Language :: Python :: 3
Classifier: License :: OSI Approved :: MIT License
Classifier: Operating System :: OS Independent
Classifier: Environment :: Console
Classifier: Topic :: Utilities
Classifier: Topic :: System :: Filesystems
Requires-Python: >=3.9
License-File: LICENSE.txt
Dynamic: author
Dynamic: author-email
Dynamic: classifier
Dynamic: description
Dynamic: description-content-type
Dynamic: home-page
Dynamic: license-file
Dynamic: requires-python
Dynamic: summary
